ydot
