Metadata-Version: 2.1
Name: ydot
Version: 0.0.6
Summary: R-like formulas for Spark Dataframes
Home-page: https://github.com/oneoffcoder/pyspark-formula
Author: Jee Vang
Author-email: vangjee@gmail.com
License: UNKNOWN
Keywords: statistics pyspark formula patsy spark dataframe regression classification data machine learning artificial intelligence
Platform: UNKNOWN
Classifier: Programming Language :: Python :: 3
Classifier: License :: OSI Approved :: Apache Software License
Classifier: Operating System :: OS Independent
Classifier: Topic :: Scientific/Engineering :: Artificial Intelligence
Classifier: Intended Audience :: Developers
Classifier: Intended Audience :: Science/Research
Classifier: Development Status :: 5 - Production/Stable
